xpattern/__init__.py
xpattern/_xobject.py
xpattern/_xpattern.py
xpattern-0.5.0.dist-info/LICENSE
xpattern-0.5.0.dist-info/WHEEL
xpattern-0.5.0.dist-info/METADATA
xpattern-0.5.0.dist-info/RECORD
