Metadata-Version: 2.1
Name: xpattern
Version: 0.5.0
Summary: Pattern Matching with XObject.
Home-page: https://github.com/zen-xu/xpattern
License: MIT
Keywords: pattern-matching,functional,pipeline
Author: ZhengYu, Xu
Author-email: zen-xu@outlook.com
Requires-Python: >=3.6.1,<4.0.0
Classifier: License :: OSI Approved :: MIT License
Classifier: Operating System :: OS Independent
Classifier: Programming Language :: Python :: 3
Classifier: Programming Language :: Python :: 3.7
Classifier: Programming Language :: Python :: 3.8
Classifier: Topic :: Software Development :: Libraries :: Python Modules
Requires-Dist: pampy (>=0.3.0,<0.4.0)
Project-URL: Repository, https://github.com/zen-xu/xpattern
